tpds/__init__.py
tpds/packages/__init__.py
tpds/packages/packages.yaml
tpds_manifest-1.0.9.dist-info/licenses/LICENSE
tpds_manifest-1.0.9.dist-info/METADATA
tpds_manifest-1.0.9.dist-info/WHEEL
tpds_manifest-1.0.9.dist-info/top_level.txt
tpds_manifest-1.0.9.dist-info/RECORD
