Metadata-Version: 2.4
Name: tpds-manifest
Version: 1.0.9
Summary: Microchip(SPG) Trust Platform Approved Package List
Maintainer-email: Microchip Technology <SPG.Tools@microchip.com>
License: (c) 2015-2023 Microchip Technology Inc. and its subsidiaries.
Classifier: License :: Other/Proprietary License
Classifier: Development Status :: 4 - Beta
Classifier: Programming Language :: Python :: 3
Classifier: Operating System :: OS Independent
Requires-Python: >=3.8
License-File: LICENSE
Requires-Dist: pyyaml
Provides-Extra: dev
Requires-Dist: flake8; extra == "dev"
Requires-Dist: black; extra == "dev"
Requires-Dist: isort; extra == "dev"
Requires-Dist: mypy; extra == "dev"
Provides-Extra: test
Requires-Dist: pytest-cov; extra == "test"
Dynamic: license-file
